aio_snowplow_tracker/__init__.py
aio_snowplow_tracker/_timer.py
aio_snowplow_tracker/_version.py
aio_snowplow_tracker/contracts.py
aio_snowplow_tracker/emitters.py
aio_snowplow_tracker/payload.py
aio_snowplow_tracker/self_describing_json.py
aio_snowplow_tracker/subject.py
aio_snowplow_tracker/tracker.py
aio_snowplow_tracker/typing.py
aio_snowplow_tracker/celery/__init__.py
aio_snowplow_tracker/celery/celery_emitter.py
aio_snowplow_tracker/redis/__init__.py
aio_snowplow_tracker/redis/redis_emitter.py
aio_snowplow_tracker/redis/redis_worker.py
aio_snowplow_tracker/test/__init__.py
aio_snowplow_tracker-1.0.2.dist-info/LICENSE
aio_snowplow_tracker-1.0.2.dist-info/METADATA
aio_snowplow_tracker-1.0.2.dist-info/WHEEL
aio_snowplow_tracker-1.0.2.dist-info/top_level.txt
aio_snowplow_tracker-1.0.2.dist-info/RECORD
