Metadata-Version: 2.1
Name: aio-snowplow-tracker
Version: 1.0.2
Summary: Asyncio Snowplow event tracker for Python. Add analytics to your Python and Django apps, webapps and games.
Home-page: https://github.com/miermans/aio-snowplow-python-tracker
Author: Anuj More, Alexander Dean, Fred Blundun, Paul Boocock, Matt Miermans
Author-email: m.miermans@gmail.com
License: Apache License 2.0
Classifier: Development Status :: 5 - Production/Stable
Classifier: Intended Audience :: Developers
Classifier: License :: OSI Approved :: Apache Software License
Classifier: Programming Language :: Python
Classifier: Programming Language :: Python :: 3
Classifier: Programming Language :: Python :: 3.7
Classifier: Programming Language :: Python :: 3.8
Classifier: Programming Language :: Python :: 3.9
Classifier: Programming Language :: Python :: 3.10
Classifier: Operating System :: OS Independent
Classifier: Framework :: AsyncIO
License-File: LICENSE
Requires-Dist: aiohttp (>=3.0.0)
Requires-Dist: typing-extensions (>=3.7.4)
Provides-Extra: celery
Requires-Dist: celery (>=4.0) ; extra == 'celery'
Provides-Extra: redis
Requires-Dist: redis (>=2.9.1) ; extra == 'redis'
Requires-Dist: gevent (>=21.1.2) ; extra == 'redis'
